itadvisor_client/__init__.py
itadvisor_client/itadvisor_client.py
itadvisor_client/ita_modules/__init__.py
itadvisor_client/ita_modules/ita_assets.py
itadvisor_client/ita_modules/ita_audit_trail.py
itadvisor_client/ita_modules/ita_authentication.py
itadvisor_client/ita_modules/ita_authentication_servers.py
itadvisor_client/ita_modules/ita_backup.py
itadvisor_client/ita_modules/ita_certificates.py
itadvisor_client/ita_modules/ita_change_request.py
itadvisor_client/ita_modules/ita_change_request_template.py
itadvisor_client/ita_modules/ita_configuration.py
itadvisor_client/ita_modules/ita_custom_properties.py
itadvisor_client/ita_modules/ita_customers.py
itadvisor_client/ita_modules/ita_customers_count.py
itadvisor_client/ita_modules/ita_equipment_browser.py
itadvisor_client/ita_modules/ita_etl_configuration.py
itadvisor_client/ita_modules/ita_genomes.py
itadvisor_client/ita_modules/ita_kpis.py
itadvisor_client/ita_modules/ita_licenses.py
itadvisor_client/ita_modules/ita_mail.py
itadvisor_client/ita_modules/ita_platform_status.py
itadvisor_client/ita_modules/ita_power_capacity.py
itadvisor_client/ita_modules/ita_power_path.py
itadvisor_client/ita_modules/ita_routing.py
itadvisor_client/ita_modules/ita_sensor_mapping.py
itadvisor_client/ita_modules/ita_struxure_on.py
itadvisor_client/ita_modules/ita_svg.py
itadvisor_client/ita_modules/ita_user_groups.py
itadvisor_client/ita_modules/ita_user_message.py
itadvisor_client/ita_modules/ita_users.py
itadvisor_client/ita_modules/ita_work_orders.py
itadvisor_client-0.0.21.dist-info/LICENSE
itadvisor_client-0.0.21.dist-info/METADATA
itadvisor_client-0.0.21.dist-info/WHEEL
itadvisor_client-0.0.21.dist-info/top_level.txt
itadvisor_client-0.0.21.dist-info/RECORD
