Metadata-Version: 2.1
Name: itadvisor_client
Version: 0.0.21
Summary: A python client for the Schneider Electric application IT Advisor.
Author-email: David Romero <dromero@dromero.dev>
Project-URL: LinkedIn, https://www.linkedin.com/in/dromero1/
Project-URL: Repository, https://github.com/dl-romero/itadvisor_client
Project-URL: Issues, https://github.com/dl-romero/itadvisor_client/issues
Keywords: struxureware,ecostruxure,schneider-electric,apc,dco,ita,itadvisor,data center operation
Classifier: Programming Language :: Python :: 3
Classifier: License :: OSI Approved :: Apache Software License
Classifier: Operating System :: OS Independent
Requires-Python: >=3.8
License-File: LICENSE
